scmm/__init__.py
scmm/agents/__init__.py
scmm/agents/eval.py
scmm/agents/genetic/__init__.py
scmm/agents/genetic/ga.py
scmm/agents/nn/__init__.py
scmm/agents/nn/nn.py
scmm/agents/potential_fields/__init__.py
scmm/agents/potential_fields/forces.py
scmm/agents/scripted/__init__.py
scmm/agents/scripted/agent_demo.py
scmm/agents/scripted/alternating_fire.py
scmm/agents/scripted/block_enemy.py
scmm/agents/scripted/dying_retreat.py
scmm/agents/scripted/focus_fire.py
scmm/agents/scripted/hybrid_attack.py
scmm/agents/scripted/kiting.py
scmm/agents/scripted/positioning.py
scmm/agents/scripted/wall_off.py
scmm/bin/__init__.py
scmm/bin/map_list.py
scmm/env/__init__.py
scmm/env/multiagentenv.py
scmm/env/micro_env/__init__.py
scmm/env/micro_env/mm_env.py
scmm/env/micro_env/maps/__init__.py
scmm/env/micro_env/maps/mm_maps.py
scmm/utils/__init__.py
scmm/utils/game_show.py
scmm/utils/game_utils.py
SC2MM-0.1.0.dist-info/LICENSE
SC2MM-0.1.0.dist-info/METADATA
SC2MM-0.1.0.dist-info/WHEEL
SC2MM-0.1.0.dist-info/top_level.txt
SC2MM-0.1.0.dist-info/RECORD
