Metadata-Version: 2.1
Name: SC2MM
Version: 0.1.0
Summary: A package for StarCraft2 Micro-Management.
Home-page: https://github.com/caiyangcy/SC2DC
Author: Cai Yang
Author-email: u6625166@anu.edu.au
License: UNKNOWN
Platform: UNKNOWN
Classifier: Programming Language :: Python :: 3
Classifier: License :: OSI Approved :: MIT License
Classifier: Operating System :: OS Independent
Requires-Python: >=3.6.10
Requires-Dist: pysc2 (>=3.0.0)
Requires-Dist: s2clientprotocol (>=4.10.1.75800.0)
Requires-Dist: absl-py (>=0.1.0)
Requires-Dist: numpy (>=1.10)
